{
  "tv": {
    "3M": ["10368"],
    "A Mark": ["10103", "10132", "10388"],
    "Action": ["10370"],
    "Admiral": ["10436", "10431"],
    "Advent": ["10135", "10339"],
    "Adventure": ["10372"],
    "Akai": ["10148", "10160", "10001", "10317", "10318", "10348", "10352", "10542", "10439", "10476", "10517"],
    "Alaron": ["10376"],
    "Albatron": ["10377"],
    "Ambassador": ["10378"],
    "America Action": ["10380"],
    "Ampro": ["10070", "10164", "10249", "10381"],
    "Amstrad": ["10053"],
    "Anam": ["10045", "10055", "10057", "10076", "10095", "10099", "10103", "10109", "10112", "10143", "10380"],
    "AOC": ["10088", "10363", "10367", "10001", "10011", "10103", "10330", "10439"],
    "Aomni": ["10354"],
    "Apex": ["10302", "10303", "10282"],
    "Apex Digital": ["10303", "10373", "10384"],
    "Archer": ["10388"],
    "Astar": ["10390"],
    "Audiovox": ["10345", "10319", "10380", "10374", "10388"],
    "Aurora Systems": ["10391"],
    "Aventura": ["10311"],
    "Belcor": ["10001", "10011", "10315"],
    "Bell & Howell": ["10393"],
    "Beng": ["10395", "10396"],
    "Blaupunkt": ["10084"],
    "Blir: Sens": ["10476", "10455", "10499"],
    "Bradford": ["10380"],
    "Brillian": ["10398"],
    "Brockwood": ["10011", "10315"],
    "Broksonic": ["10143", "10166", "10174", "10431"],
    "Bush": ["10399"],
    "Byd: Sign": ["10400"],
    "Candle": ["10001", "10002", "10003", "10011", "10439", "10372", "10543"],
    "Canon": ["10402", "10403"],
    "Capehart": ["10059"],
    "Carnibale": ["10001", "10439"],
    "Carver": ["10415", "10405"],
    "Casio": ["10406", "10407"],
    "CCE": ["10408"],
    "Celebrity": ["10409"],
    "Celera": ["10303"],
    "Cetronic": ["10045"],
    "Changhong": ["10303"],
    "Citizen": ["10001", "10002", "10003", "10011", "10045", "10092", "10094", "10132", "10439", "10374", "10372", "10543", "10517"],
    "Clarion": ["10380"],
    "Classic": ["10045"],
    "Coby": ["10412", "10011", "10275"],
    "Commercial Solutions": ["10413"],
    "Compaq": ["10414"],
    "Concerto": ["10011", "10543"],
    "Contec": ["10041", "10045", "10051", "10052", "10380"],
    "Corena System": ["10301"],
    "Coronado": ["10132"],
    "Craig": ["10045", "10055", "10157", "10049", "10159", "10380", "10258"],
    "Crosley": ["10415"],
    "Crown": ["10045", "10132", "10380"],
    "Curtis Mathes": ["10001", "10092", "10011", "10132", "10365", "10413", "10415", "10393", "10319", "10436", "10542", "10439", "10368", "10504", "10543", "10271"],
    "CXC": ["10045", "10380"],
    "Cyberhome": ["10416"],
    "Cytron": ["10417", "10418"],
    "Daewoo": ["10011", "10022", "10023", "10038", "10045", "10046", "10056", "10068", "10073", "10094", "10098", "10102", "10105", "10108", "10111", "10114", "10116", "10118", "10119", "10127", "10132", "10246", "10319", "10374", "10315", "10188"],
    "Daytron": ["10011", "10132", "10315"],
    "Dell": ["10148", "10314"],
    "Delta": ["10419"],
    "Denon": ["10368", "10421"],
    "Diamond Vision": ["10422", "10423"],
    "Digi Link": ["10172"],
    "Digistar": ["10424"],
    "Digital Lifestyles": ["10425", "10426"],
    "Digital Projection, Inc.": ["10427", "10429"],
    "Dream Vision": ["10430"],
    "Dumont": ["10011"],
    "Durabrand": ["10431", "10380", "10315", "10311", "10434", "10388", "10435"],
    "DWIN": ["10436"],
    "Dynasty": ["10045"],
    "Dynatech": ["10063"],
    "Dynex": ["10091", "10347", "10366"],
    "Eiki": ["10253", "10402"],
    "Electrograph": ["10354", "10486"],
    "Electroband": ["10409"],
    "Electrohome": ["10074", "10132", "10431"],
    "Element": ["10335", "10259", "10273", "10283"],
    "Emerson": ["10001", "10012", "10013", "10029", "10033", "10045", "10048", "10049", "10051", "10052", "10091", "10011", "10132", "10137", "10139", "10141", "10157", "10140", "10184", "10185", "10186", "10187", "10188", "10190", "10192", "10193", "10194", "10195", "10196", "10197", "10198", "10199", "10200", "10201", "10202", "10355", "10393", "10319", "10431", "10380", "10315", "10311", "10505"],
    "Emprex": ["10425"],
    "Envision": ["10439", "10358", "10330", "10001"],
    "Epson": ["10364"],
    "Erae": ["10442"],
    "ESA": ["10317", "10318", "10311"],
    "Fisher": ["10013", "10058", "10393"],
    "Fujitsu": ["10149", "10228", "10333", "10334", "10376"],
    "Funai": ["10033", "10045", "10380", "10311", "10376", "10452"],
    "FutureTech": ["10045", "10380"],
    "Gateway": ["10310", "10486"],
    "GE": ["10001", "10014", "10015", "10038", "10057", "10070", "10083", "10011", "10121", "10133", "10141", "10145", "10413", "10319", "10315", "10489", "10484"],
    "Gilbraiter": ["10001", "10011", "10439", "10315"],
    "Go Video": ["10443", "10479", "10476"],
    "Goodmans": ["10445"],
    "GPX": ["10276"],
    "Gradiente": ["10040"],
    "Grundig": ["10288", "10289"],
    "Grunpy": ["10380", "10376"],
    "GVA": ["10278"],
    "H&B": ["10301"],
    "Haier": ["10026", "10322", "10323", "10324", "10325", "10326", "10434", "10373", "10067"],
    "Hall Mark": ["10011", "10315"],
    "Hanns.G": ["10447"],
    "Hannspree": ["10448", "10449", "10447", "10263", "10264"],
    "Harley Davidson": ["10451", "10376", "10452"],
    "Harman Kardon": ["10034", "10180", "10181", "10415"],
    "Harvard": ["10380", "10453"],
    "Havermy": ["10436"],
    "Helios": ["10301"],
    "Hello Kitty": ["10319"],
    "Hewlett Packard": ["10456", "10330", "10458"],
    "Hisense": ["10266", "10011", "10279", "10280", "10373", "10459", "10462"],
    "Hitachi": ["10017", "10011", "10015", "10016", "10001", "10018", "10029", "10043", "10072", "10132", "10144", "10147", "10203", "10204", "10206", "10207", "10208", "10210", "10211", "10368", "10452", "10543"],
    "HP": ["10357"],
    "Humax": ["10143"],
    "Hyperion": ["10011"],
    "Hyundai": ["10460", "10461"],
    "I-Inc": ["10463"],
    "ILO": ["10091", "10343", "10362", "10356"],
    "Infinity": ["10415", "10148"],
    "Infocus": ["10464", "10364", "10466", "10467"],
    "Initial": ["10356"],
    "Inkel": ["10120"],
    "Insignia": ["10091", "10366", "10311", "10417", "10274"],
    "JBL": ["10148", "10415"],
    "JCPenny": ["10001", "10011", "10014", "10015", "10030", "10035", "10092", "10132", "10145"],
    "Jensen": ["10019", "10234"],
    "JVC": ["10261", "10270", "10038", "10040", "10079", "10239", "10550"],
    "Kawasho": ["10470"],
    "KDS": ["10335"],
    "KEC": ["10045", "10380"],
    "Kenwood": ["10001", "10229", "10011", "10439", "10315"],
    "Klegg": ["10354"],
    "KLH": ["10341", "10303"],
    "Kloss": ["10002", "10060", "10001", "10372"],
    "KMC": ["10132"],
    "Knoll Systems": ["10467"],
    "Konka": ["10473", "10475", "10476", "10477"],
    "Kost": ["10478", "10479"],
    "Kreisen": ["10480", "10479"],
    "KT": ["10001", "10045", "10132", "10140", "10308"],
    "KTV": ["10380", "10439"],
    "LG (Goldstar)": ["10011", "10093", "10103", "10113", "10118", "10132", "10346", "10315", "10439"],
    "Lloyd's": ["10452"],
    "Lodgenet": ["10069"],
    "Loewe": ["10481"],
    "Logik": ["10069"],
    "Luce": ["10358", "10483"],
    "Luxman": ["10011", "10543"],
    "LXI": ["10013", "10021", "10053", "10034", "10145", "10148", "10413", "10415", "10393", "10303", "10315"],
    "Magnasonic": ["10001", "10011", "10348"],
    "Magnavox": ["10001", "10003", "10011", "10060", "10061", "10062", "0064", "10065", "10066", "10086", "10088", "10118", "10132", "10145", "10148", "10192", "10212", "10236", "10244", "10312", "10332", "10415", "10439", "10356", "10505", "10452", "10330", "10376", "10126"],
    "Magnin": ["10484"],
    "Marantz": ["10001", "10074", "10148", "10415", "10439"],
    "Matsui": ["10148"],
    "Matsushita": ["10485"],
    "Maxent": ["10486", "10487"],
    "MB Quart": ["10315"],
    "Megatron": ["10315", "10368", "10388", "10435"],
    "Memorex": ["10013", "10069", "10091", "10011", "10393", "10431", "10315", "10376", "10516"],
    "Metz": ["10084"],
    "MGA": ["10001", "10011", "10033", "10044", "10050", "10074", "10315", "10439", "10484"],
    "Midland": ["10413"],
    "Minerva": ["10084"],
    "Mintek": ["10356"],
    "Mitsubishi": ["10216", "10011", "10030", "10033", "10034", "10041", "10044", "10089", "10115", "10160", "10167", "10168", "10214", "10001", "10245", "10436", "10315"],
    "Monivision": ["10377"],
    "Montgomery Ward": ["10185", "10217", "10218", "10219", "10220"],
    "Motorola": ["10436", "10335"],
    "Moxell": ["10335"],
    "MTC": ["10001", "10011", "10439", "10315", "10543"],
    "Multitech": ["10380"],
    "NAD": ["10021", "10031", "10303", "10315", "10543"],
    "Nakamichi": ["10491"],
    "Naxa": ["10492"],
    "NEC": ["10001", "10013", "10022", "10025", "10030", "10041", "10057", "10121", "10125", "10011", "10235", "10439", "10315", "10543", "10405"],
    "NetTV": ["10486"],
    "Nikei": ["10045"],
    "Nikko": ["10001", "10315", "10439", "10374"],
    "Niko": ["10493"],
    "Noblex": ["10494"],
    "Norcent": ["10373", "10330", "10495", "10493"],
    "Norwood Micro": ["10362", "10498"],
    "NTC": ["10374"],
    "NuVision": ["10502"],
    "Olevia": ["10011", "10342", "10535", "10315"],
    "Olympus": ["10503"],
    "Onwa": ["10045", "10380"],
    "Optonica": ["10025", "10334", "10235", "10436"],
    "Optimus": ["10485", "10393", "10504", "10505"],
    "Optoma": ["10506", "10448"],
    "Orion": ["10431", "10376", "10516"],
    "Panasonic": ["10076", "10010", "10038", "10057", "10005", "10148", "10150", "10169", "10308", "10359", "10485"],
    "Penney": ["10001", "10011", "10413", "10303", "10315", "10439", "10484", "10489", "10388"],
    "Philco": ["10001", "10003", "10011", "10030", "10045", "10057", "10060", "10061", "10064", "10065", "10118", "10132", "10148", "10415", "10439", "10315"],
    "Philips": ["10148", "10321", "10011", "10040", "10060", "10067", "10132", "10145", "10001", "10222", "10003", "10371", "10415", "10479"],
    "Pilot": ["10001", "10011", "10439", "10315"],
    "Pioneer": ["10504", "10024", "10029", "10031", "10032", "10011", "10248", "10254", "10304", "10001"],
    "Polaroid": ["10335", "10338", "10339", "10340", "10341", "10303", "10417", "10362", "10478", "10301", "10476"],
    "Portland": ["10011", "10132", "10374", "10315", "10335", "10424", "10476"],
    "Proscan": ["10133", "10249", "10413", "10262", "10257", "10268", "10067", "10269"],
    "Proton": ["10059", "10011", "10103", "10132", "10165", "10251", "10315", "10388"],
    "Protron": ["10507", "10508"],
    "Proview": ["10335"],
    "Pulsar": ["10011", "10315"],
    "Puneet": ["10425"],
    "PVision": ["10442"],
    "Quasar": ["10038", "10057", "10243", "10308", "10485"],
    "Radio Shack": ["10025", "10045", "10048", "10011", "10118", "10132", "10001", "10235"],
    "RCA": ["10001", "10004", "10006", "10011", "10029", "10030", "10057", "10083", "10133", "10145", "10161", "10171", "10232", "10371", "10413", "10484", "10315", "10256", "10272"],
    "Realistic": ["10013", "10025", "10045", "10048", "10001", "10011", "10235", "10393", "10380", "10315", "10439", "10543"],
    "Revolution HD": ["10354"],
    "Roctec": ["10237"],
    "Runco": ["10152", "10153", "10001", "10250", "10336", "10337", "10439"],
    "Sampo": ["10001", "10059", "10011", "10486", "10439"],
    "Samsung": ["10305", "10265", "10001", "10012", "10051", "10092", "10011", "10118", "10124", "10132", "10145", "10176", "10306", "10542", "10315", "10439", "10479", "10408", "10543"],
    "Sansui": ["10431", "10452", "10516", "10517"],
    "Sanyo": ["10013", "10026", "10027", "10037", "10041", "10054", "10058", "10078", "10253", "10393", "10402", "10484"],
    "Sceptre": ["10313", "10067"],
    "Scimitsu": ["10011", "10315"],
    "Scott": ["10033", "10045", "10049", "10011", "10132", "10380", "10315", "10376"],
    "Scotch": ["10315"],
    "Sears": ["10011", "10013", "10021", "10033", "10035", "10078", "10092", "10132", "10145", "10244", "10413", "10415", "10393", "10303", "10315", "10311", "10543", "10376", "10452"],
    "Seiki": ["10259", "10283", "10284", "10285", "10286", "10287"],
    "Seleco": ["10368", "10430"],
    "Sharp": ["10260", "10020", "10025", "10028", "10033", "10034", "10132", "10151", "10235", "10236", "10361", "10375", "10436", "10011"],
    "Sharper Image": ["10518"],
    "Sherwood": ["10120"],
    "Shogun": ["10315"],
    "Siemens": ["10084"],
    "Signature": ["10069", "10011"],
    "Signature 2000": ["10011"],
    "Signet": ["10519", "10478", "10520"],
    "Sim2 Multimedia": ["10430"],
    "Simpson": ["10001"],
    "Skyworth": ["10522"],
    "Solarism": ["10523"],
    "Sole": ["10358", "10483", "10301", "10479", "10354"],
    "Sony": ["10043", "10075", "10117", "10130", "10067", "10170", "10238", "10247", "10309", "10409", "10452"],
    "Soundesign": ["10003", "10033", "10045", "10011", "10380", "10315", "10376"],
    "Sova": ["10507"],
    "Soyo": ["10425", "10463", "10524", "10525", "10479"],
    "Spectricon": ["10103", "10011", "10388"],
    "Spectroniq": ["10335"],
    "Squareview": ["10311"],
    "SSS": ["10011", "10045", "10380", "10315"],
    "Starlite": ["10011", "10380"],
    "Studio Experience": ["10377"],
    "Sunbrite": ["10528", "10529"],
    "Superscan": ["10436", "10530"],
    "Supremacy": ["10002", "10372"],
    "Supreme": ["10409"],
    "SVA": ["10373", "10479", "10301", "10532", "10533"],
    "Sylvania": ["10001", "10003", "10008", "10011", "10060", "10061", "10064", "10118", "10126", "10065", "10145", "10148", "10155", "10311", "10355", "10415", "10439"],
    "Symphonic": ["10380", "10311", "10452", "10505"],
    "Syntax": ["10342", "10535", "10315"],
    "Tandy": ["10034", "10436"],
    "Tashiko": ["10537"],
    "Tatung": ["10057", "10063", "10388", "10458", "10362"],
    "TCL": ["10256", "10371", "10267"],
    "Teac": ["10379", "10281"],
    "Technics": ["10080", "10076", "10485"],
    "Technol Ace": ["10376"],
    "Techview": ["10539", "10541"],
    "Techwood": ["10011", "10388", "10543"],
    "Telemagic": ["10402"],
    "Teknika": ["10001", "10002", "10003", "10011", "10030", "10033", "10036", "10045", "10069", "10074", "10092", "10094", "10132", "10415", "10380", "10374", "10315", "10543", "10376"],
    "Telefunken": ["10039", "10047", "10241", "10242", "10542", "10543", "10544"],
    "Telerent": ["10069"],
    "Tera": ["10156"],
    "Thomas": ["10452"],
    "TMK": ["10011", "10315", "10543", "10378"],
    "Toshiba": ["10021", "10013", "10035", "10041", "10052", "10063", "10092", "10142", "10146", "10178", "10179", "10393", "10303", "10464", "10419", "10517"],
    "Totevision": ["10132"],
    "TruTech": ["10353"],
    "TVS": ["10431"],
    "Ultra": ["10547", "10508"],
    "Universal": ["10014", "10015"],
    "Upstar": ["10277"],
    "US Logic": ["10362"],
    "Vector Research": ["10001", "10439"],
    "Venturer": ["10315"],
    "Victor": ["10550"],
    "Video Concepts": ["10160"],
    "Vidikron": ["10255", "10415"],
    "Vidtech": ["10011", "10315"],
    "Viewsonic": ["10363", "10088", "10330", "10331", "10349", "10486", "10530", "10503"],
    "Viking": ["10372"],
    "Viore": ["10316"],
    "Visart": ["10551"],
    "Vito": ["10360"],
    "Vizio": ["10011", "10315", "10351", "10530"],
    "Wards": ["10011", "10014", "10015", "10025", "10033", "10061", "10062", "10064", "10065", "10069", "10071", "10132", "10148", "10001", "10235", "10415", "10315", "10439", "10489", "10543", "10376"],
    "Waycon": ["10303"],
    "White Westinghouse": ["10091", "10319", "10320", "10327", "极速影院", "10329", "10067", "10431", "10409"],
    "Winbook": ["10362"],
    "Wooyoung": ["10307"],
    "Wyse": ["10330"],
    "Xoceco": ["10552"],
    "Yamaha": ["10001", "10011", "10439", "10315"],
    "York": ["10011"],
    "Zenith": ["10009", "10069", "10070", "10090", "10094", "10431", "10315", "10374", "10452", "10516"],
    "Zonda": ["10103", "10388"]
  },
  "audio": {
    "Adcom": ["20088", "20098", "20218", "20147", "20233"],
    "Aiwa": ["20142", "20182", "20025", "20141", "20022", "20110"],
    "Akai": ["20128"],
    "Anam": ["20026", "极速影院", "20189"],
    "Anthem": ["20004"],
    "B&K": ["20102", "20103"],
    "Bose": ["20007", "20185", "20131"],
    "Carver": ["20253", "20013", "20037", "20060", "20068", "20148", "20221", "20226", "20245", "20250", "20015"],
    "Clarion": ["20132"],
    "Coby": ["20010", "20017"],
    "Denon": ["20041", "20234", "20111", "20149", "20150", "20152", "20232", "20003"],
    "Enlightened": ["20105"],
    "Everquest": ["20032"],
    "Fisher": ["20037", "20015", "20083", "20207"],
    "Fosgate Audionic": ["20153"],
    "Haier": ["20019", "20023"],
    "Harman Kardon": ["20205", "20208", "20153", "20228", "20229", "20249"],
    "Hitachi": ["20035", "20040", "20027", "20202"],
    "ILive": ["20049", "20050"],
    "Inkel": ["20012"],
    "Insignia": ["20061"],
    "JCPenny": ["20016", "20108"],
    "Jensen": ["20065"],
    "JVC": ["20112"],
    "Kenwood": ["20012", "20206", "20231", "20033", "20015", "20211", "20212", "20213", "20214", "20215", "20222", "20230", "20134", "20246"],
    "Lexicon": ["20125", "20156", "20158", "20159"],
    "LG (Goldstar)": ["20069", "20077", "20018", "20192"],
    "Lotte": ["20191", "20193"],
    "Luxmann": ["20042"],
    "LXI": ["20084"],
    "Magnavox": ["20013", "20092"],
    "Marantz": ["20013", "20093", "20047", "20072", "20063", "20203", "20221", "20250"],
    "Maxell": ["20078"],
    "McIntosh": ["20160"],
    "MCS": ["20016"],
    "Mitsubishi": ["20164", "20165"],
    "NAD": ["极速影院"],
    "Nakamichi": ["20167", "20047"],
    "Niles": ["20168"],
    "Onkyo": ["20178", "20053", "20113", "20114", "20024", "20177", "20179", "20223", "20224", "20251"],
    "Optimus": ["20029", "20033", "极速影院"],
    "Outlaw": ["20183"],
    "Panasonic": ["20126", "20014", "20039", "20094", "20194", "20200"],
    "Parasound": ["20254"],
    "Philips": ["20009", "20301", "20302", "20303", "20093", "20013", "20172", "20124"],
    "Pioneer": ["20082", "20021", "20046", "极速影院", "20057", "20073", "20076", "20096", "20001", "20054", "20237", "20238", "20239", "20240", "20241", "20242", "20243", "20244"],
    "Proceed": ["20006", "20248", "20252"],
    "Quasar": ["20014", "20094"],
    "RCA": ["20062", "20106", "20120", "20138", "20056", "20123"],
    "极速影院": ["20011", "20030", "20084", "20002", "20026", "20101"],
    "Rotel": ["20089", "20080", "20091"],
    "Samsung": ["20304", "20197", "20198", "20199", "20306"],
    "Sansui": ["20116", "20013", "20124", "20047"],
    "Sanyo": ["20187"],
    "Scott": ["20026", "20097"],
    "Sharp": ["20139", "20058", "20033", "20100", "20132", "20133", "20134", "20127"],
    "Sherwood": ["20045", "20031", "20247"],
    "Sony": ["20008", "20176", "20005", "20025", "极速影院", "20145", "20090", "20170", "20195", "20209", "20216", "20305"],
    "Soundesign": ["20043"],
    "SSI": ["20075"],
    "Taekwang": ["20128", "20186", "20195"],
    "Teac": ["20066", "20067", "20026", "20190"],
    "Technics": ["20126", "20094", "20109", "20014", "20137"],
    "Thomson": ["20217"],
    "Toshiba": ["20155", "20118", "20237", "20255"],
    "Victor": ["20020", "20112"],
    "Vizio": ["20180"],
    "Wards": ["20015"],
    "Yamaha": ["20140", "20166", "20201", "20028", "20033", "20038", "20074", "20132", "20175", "20204", "20210", "20219", "20220", "20227", "20235", "20236"],
    "Zantek": ["20174"]
  }
}